crispr_tools/__init__.py
crispr_tools-0.0.1.dist-info/METADATA
crispr_tools-0.0.1.dist-info/WHEEL
crispr_tools-0.0.1.dist-info/top_level.txt
crispr_tools-0.0.1.dist-info/RECORD
