Metadata-Version: 2.1
Name: crispr-tools
Version: 0.0.1
Summary: crispr_tools - Analysis Tools for CRISPR Screen Design and Analysis
Home-page: UNKNOWN
Author: Michael E. Vinyard - Harvard University - Massachussetts General Hospital - Broad Institute of MIT and Harvard
Author-email: mvinyard@broadinstitute.org
License: MIT
Platform: UNKNOWN
Classifier: Development Status :: 2 - Pre-Alpha
Classifier: Programming Language :: Python :: 3.8
Classifier: Intended Audience :: Science/Research
Classifier: Topic :: Scientific/Engineering :: Bio-Informatics
Requires-Python: >3.8.0
Requires-Dist: matplotlib (>=3.4)
Requires-Dist: anndata (>=0.7.1)
Requires-Dist: numpy (>=1.19.2)
Requires-Dist: pandas (>=1.1.2)
Requires-Dist: biopython (>=1.79)
